odoo/addons/delivery_carrier_picking_valid_dangerous_goods/README.rst
odoo/addons/delivery_carrier_picking_valid_dangerous_goods/__init__.py
odoo/addons/delivery_carrier_picking_valid_dangerous_goods/__manifest__.py
odoo/addons/delivery_carrier_picking_valid_dangerous_goods/i18n/delivery_carrier_picking_valid_dangerous_goods.pot
odoo/addons/delivery_carrier_picking_valid_dangerous_goods/i18n/it.po
odoo/addons/delivery_carrier_picking_valid_dangerous_goods/models/__init__.py
odoo/addons/delivery_carrier_picking_valid_dangerous_goods/models/delivery_carrier.py
odoo/addons/delivery_carrier_picking_valid_dangerous_goods/readme/CONTRIBUTORS.md
odoo/addons/delivery_carrier_picking_valid_dangerous_goods/readme/DESCRIPTION.md
odoo/addons/delivery_carrier_picking_valid_dangerous_goods/readme/USAGE.md
odoo/addons/delivery_carrier_picking_valid_dangerous_goods/static/description/icon.png
odoo/addons/delivery_carrier_picking_valid_dangerous_goods/static/description/index.html
odoo/addons/delivery_carrier_picking_valid_dangerous_goods/tests/__init__.py
odoo/addons/delivery_carrier_picking_valid_dangerous_goods/tests/test_delivery_carrier_valid_dangerous_goods.py
odoo/addons/delivery_carrier_picking_valid_dangerous_goods/views/delivery_carrier.xml
odoo_addon_delivery_carrier_picking_valid_dangerous_goods-18.0.1.0.0.4.dist-info/METADATA
odoo_addon_delivery_carrier_picking_valid_dangerous_goods-18.0.1.0.0.4.dist-info/WHEEL
odoo_addon_delivery_carrier_picking_valid_dangerous_goods-18.0.1.0.0.4.dist-info/top_level.txt
odoo_addon_delivery_carrier_picking_valid_dangerous_goods-18.0.1.0.0.4.dist-info/RECORD
