Metadata-Version: 2.1
Name: odoo-addon-delivery_carrier_picking_valid_dangerous_goods
Version: 18.0.1.0.0.4
Requires-Python: >=3.10
Requires-Dist: odoo-addon-delivery_carrier_picking_valid==18.0.*
Requires-Dist: odoo-addon-l10n_eu_product_adr_dangerous_goods==18.0.*
Requires-Dist: odoo==18.0.*
Summary: Checks if a transfer matches carrier dangerous goods restrictions
Home-page: https://github.com/OCA/delivery-carrier
License: AGPL-3
Author: Camptocamp, BCIM, Odoo Community Association (OCA)
Author-email: support@odoo-community.org
Classifier: Programming Language :: Python
Classifier: Framework :: Odoo
Classifier: Framework :: Odoo :: 18.0
Classifier: License :: OSI Approved :: GNU Affero General Public License v3
